earth2observe/__init__.py
earth2observe/abstractdatasource.py
earth2observe/chirps.py
earth2observe/earth2observe.py
earth2observe/ecmwf.py
earth2observe/s3.py
earth2observe/gee/__init__.py
earth2observe/gee/data.py
earth2observe/gee/dataset.py
earth2observe/gee/features.py
earth2observe/gee/gee.py
earth2observe/gee/imagecollection.py
earth2observe/gee/images.py
earth2observe-0.2.2.dist-info/AUTHORS.rst
earth2observe-0.2.2.dist-info/LICENSE.md
earth2observe-0.2.2.dist-info/METADATA
earth2observe-0.2.2.dist-info/WHEEL
earth2observe-0.2.2.dist-info/top_level.txt
earth2observe-0.2.2.dist-info/RECORD
