Metadata-Version: 2.1
Name: earth2observe
Version: 0.2.2
Summary: remote sensing package
Home-page: https://github.com/MAfarrag/earth2observe
Author: Mostafa Farrag
Author-email: moah.farag@gmail.come
License: GNU General Public License v3
Keywords: remote sensing,ecmwf
Classifier: Development Status :: 5 - Production/Stable
Classifier: Environment :: Console
Classifier: License :: OSI Approved :: GNU General Public License v3 (GPLv3)
Classifier: Natural Language :: English
Classifier: Programming Language :: Python :: 3
Classifier: Programming Language :: Python :: 3.7
Classifier: Programming Language :: Python :: 3.8
Classifier: Programming Language :: Python :: 3.9
Classifier: Topic :: Scientific/Engineering :: GIS
Classifier: Intended Audience :: Science/Research
Classifier: Intended Audience :: Developers
License-File: LICENSE.md
License-File: AUTHORS.rst
Requires-Dist: boto3 (>=1.26.50)
Requires-Dist: earthengine-api (>=0.1.324)
Requires-Dist: ecmwf-api-client (>=1.6.3)
Requires-Dist: gdal (>=3.5.3)
Requires-Dist: joblib (>=1.2.0)
Requires-Dist: loguru (>=0.6.0)
Requires-Dist: netCDF4 (>=1.6.1)
Requires-Dist: numpy (==1.24.1)
Requires-Dist: pandas (>=1.4.4)
Requires-Dist: pathlib (>=1.0.1)
Requires-Dist: pip (>=22.3.1)
Requires-Dist: pyramids-gis (>=0.3.2)
Requires-Dist: PyYAML (>=6.0)
Requires-Dist: requests (>=2.28.1)
Requires-Dist: serapeum-utils (>=0.1.1)
